README.md
pyproject.toml
setup.py
konorutils/__init__.py
konorutils/fast.py
konorutils.egg-info/PKG-INFO
konorutils.egg-info/SOURCES.txt
konorutils.egg-info/dependency_links.txt
konorutils.egg-info/requires.txt
konorutils.egg-info/top_level.txt