Metadata-Version: 2.1
Name: konorutils
Version: 0.0.4
Summary: Some utils functions
Home-page: https://github.com/KonorOko
Author: Konor
Author-email: emilioxkonor@gmail.com
License: MIT
Requires-Dist: pandas
Requires-Dist: numpy
Requires-Dist: matplotlib
Requires-Dist: scikit-learn
Requires-Dist: setuptools>=40.8.0
Requires-Dist: wheel
